{
  "name": "LED 矩阵配置",
  "description": "8x8 LED 矩阵显示配置",
  "mcu": "STM32F407VETx",
  "peripherals": ["SPI1", "GPIO"],
  "pins": [
    {"pin": "PA5", "signal": "SPI1_SCK", "mode": "Full_Duplex_Master"},
    {"pin": "PA7", "signal": "SPI1_MOSI", "mode": "Full_Duplex_Master"},
    {"pin": "PA4", "signal": "GPIO_Output", "label": "LED_CS"}
  ],
  "config": {
    "SPI1": {
      "Mode": "SPI_MODE_MASTER",
      "Direction": "SPI_DIRECTION_1LINE",
      "DataSize": "SPI_DATASIZE_8BIT",
      "CLKPolarity": "SPI_POLARITY_LOW",
      "CLKPhase": "SPI_PHASE_1EDGE",
      "BaudRatePrescaler": "SPI_BAUDRATEPRESCALER_16"
    }
  },
  "led_matrix": {
    "size": "8x8",
    "color": "Single / RGB",
    "driver": "MAX7219 / TM1637",
    "cascade": "up to 8 modules",
    "interface": "SPI"
  },
  "nvic": {},
  "clock": {
    "hse": 8,
    "sysclk": 168
  }
}
